testxxyy/__init__.py
testxxyy/core.py
testxxyy-0.1.4.dist-info/METADATA
testxxyy-0.1.4.dist-info/WHEEL
testxxyy-0.1.4.dist-info/top_level.txt
testxxyy-0.1.4.dist-info/RECORD
