Metadata-Version: 2.4
Name: testxxyy
Version: 0.1.4
Summary: Test library
Requires-Python: >=3.7
